napari_zulip/__init__.py
napari_zulip/_widget.py
napari_zulip/napari.yaml
napari_zulip/_tests/__init__.py
napari_zulip/_tests/test_widget.py
napari_zulip-0.0.2.dist-info/LICENSE
napari_zulip-0.0.2.dist-info/METADATA
napari_zulip-0.0.2.dist-info/WHEEL
napari_zulip-0.0.2.dist-info/entry_points.txt
napari_zulip-0.0.2.dist-info/top_level.txt
napari_zulip-0.0.2.dist-info/RECORD
