Metadata-Version: 2.1
Name: napari-zulip
Version: 0.0.2
Summary: A simple plugin for interacting with Zulip from napari
Home-page: https://github.com/kephale/napari-zulip
Author: Kyle Harrington
Author-email: czi@kyleharrington.com
License: BSD-3-Clause
Project-URL: Bug Tracker, https://github.com/kephale/napari-zulip/issues
Project-URL: Documentation, https://github.com/kephale/napari-zulip#README.md
Project-URL: Source Code, https://github.com/kephale/napari-zulip
Project-URL: User Support, https://github.com/kephale/napari-zulip/issues
Classifier: Development Status :: 2 - Pre-Alpha
Classifier: Framework :: napari
Classifier: Intended Audience :: Developers
Classifier: License :: OSI Approved :: BSD License
Classifier: Operating System :: OS Independent
Classifier: Programming Language :: Python
Classifier: Programming Language :: Python :: 3
Classifier: Programming Language :: Python :: 3 :: Only
Classifier: Programming Language :: Python :: 3.9
Classifier: Programming Language :: Python :: 3.10
Classifier: Topic :: Scientific/Engineering :: Image Processing
Requires-Python: >=3.9
License-File: LICENSE
Requires-Dist: numpy
Requires-Dist: magicgui
Requires-Dist: qtpy
Requires-Dist: zulip
Provides-Extra: testing
Requires-Dist: tox ; extra == 'testing'
Requires-Dist: pytest ; extra == 'testing'
Requires-Dist: pytest-cov ; extra == 'testing'
Requires-Dist: pytest-qt ; extra == 'testing'
Requires-Dist: napari ; extra == 'testing'
Requires-Dist: pyqt5 ; extra == 'testing'
